setup.py
PyNSim.egg-info/PKG-INFO
PyNSim.egg-info/SOURCES.txt
PyNSim.egg-info/dependency_links.txt
PyNSim.egg-info/top_level.txt
pynsim/__init__.py
pynsim/history.py
pynsim/components/__init__.py
pynsim/components/component.py
pynsim/components/history.py
pynsim/engines/__init__.py
pynsim/engines/engine.py
pynsim/simulators/__init__.py
pynsim/simulators/simulator.py
test/test_history.py
test/test_overhead.py