Metadata-Version: 1.1
Name: PyNSim
Version: 0.1.4
Summary: An generic simulator for water resources.
Home-page: http://packages.python.org/pynsim
Author: Stephen Knox
Author-email: stephen.knox@manchester.ac.uk
License: GPLv3
Keywords: pynsim simulation network agent
Platform: UNKNOWN
Classifier: Programming Language :: Python
Classifier: Programming Language :: Python :: Implementation :: PyPy
Classifier: Operating System :: OS Independent
Classifier: Natural Language :: English
Classifier: Development Status :: 1 - Planning
Classifier: Intended Audience :: Developers
Classifier: License :: OSI Approved :: GNU General Public License v3 (GPLv3)
